mlflow_plugin_proxy_auth/__init__.py
mlflow_plugin_proxy_auth/proxy_auth_header_provider.py
mlflow_plugin_proxy_auth-0.1.1.dist-info/LICENSE
mlflow_plugin_proxy_auth-0.1.1.dist-info/METADATA
mlflow_plugin_proxy_auth-0.1.1.dist-info/WHEEL
mlflow_plugin_proxy_auth-0.1.1.dist-info/entry_points.txt
mlflow_plugin_proxy_auth-0.1.1.dist-info/top_level.txt
mlflow_plugin_proxy_auth-0.1.1.dist-info/RECORD
