Metadata-Version: 2.1
Name: mlflow-plugin-proxy-auth
Version: 0.1.1
Summary: Provides authentication to Mlflow server using Proxy-Authorization header.
Home-page: https://github.com/LordMathis/mlflow-plugin-proxy-auth
Author: Matúš Námešný
Author-email: matus@namesny.com
License-File: LICENSE
Requires-Dist: mlflow
